anton_testing_deleteme_123-3.0.0a1.dist-info/licenses/LICENSE
sentry_sdk_alpha/__init__.py
sentry_sdk_alpha/_compat.py
sentry_sdk_alpha/_init_implementation.py
sentry_sdk_alpha/_log_batcher.py
sentry_sdk_alpha/_lru_cache.py
sentry_sdk_alpha/_queue.py
sentry_sdk_alpha/_types.py
sentry_sdk_alpha/_werkzeug.py
sentry_sdk_alpha/api.py
sentry_sdk_alpha/attachments.py
sentry_sdk_alpha/client.py
sentry_sdk_alpha/consts.py
sentry_sdk_alpha/debug.py
sentry_sdk_alpha/envelope.py
sentry_sdk_alpha/feature_flags.py
sentry_sdk_alpha/logger.py
sentry_sdk_alpha/monitor.py
sentry_sdk_alpha/py.typed
sentry_sdk_alpha/scope.py
sentry_sdk_alpha/scrubber.py
sentry_sdk_alpha/serializer.py
sentry_sdk_alpha/session.py
sentry_sdk_alpha/sessions.py
sentry_sdk_alpha/spotlight.py
sentry_sdk_alpha/tracing.py
sentry_sdk_alpha/tracing_utils.py
sentry_sdk_alpha/transport.py
sentry_sdk_alpha/types.py
sentry_sdk_alpha/utils.py
sentry_sdk_alpha/worker.py
sentry_sdk_alpha/ai/__init__.py
sentry_sdk_alpha/ai/monitoring.py
sentry_sdk_alpha/ai/utils.py
sentry_sdk_alpha/crons/__init__.py
sentry_sdk_alpha/crons/api.py
sentry_sdk_alpha/crons/consts.py
sentry_sdk_alpha/crons/decorator.py
sentry_sdk_alpha/integrations/__init__.py
sentry_sdk_alpha/integrations/_asgi_common.py
sentry_sdk_alpha/integrations/_wsgi_common.py
sentry_sdk_alpha/integrations/aiohttp.py
sentry_sdk_alpha/integrations/anthropic.py
sentry_sdk_alpha/integrations/argv.py
sentry_sdk_alpha/integrations/ariadne.py
sentry_sdk_alpha/integrations/arq.py
sentry_sdk_alpha/integrations/asgi.py
sentry_sdk_alpha/integrations/asyncio.py
sentry_sdk_alpha/integrations/asyncpg.py
sentry_sdk_alpha/integrations/atexit.py
sentry_sdk_alpha/integrations/aws_lambda.py
sentry_sdk_alpha/integrations/beam.py
sentry_sdk_alpha/integrations/boto3.py
sentry_sdk_alpha/integrations/bottle.py
sentry_sdk_alpha/integrations/chalice.py
sentry_sdk_alpha/integrations/clickhouse_driver.py
sentry_sdk_alpha/integrations/cloud_resource_context.py
sentry_sdk_alpha/integrations/cohere.py
sentry_sdk_alpha/integrations/dedupe.py
anton_testing_deleteme_123-3.0.0a1.dist-info/METADATA
anton_testing_deleteme_123-3.0.0a1.dist-info/WHEEL
anton_testing_deleteme_123-3.0.0a1.dist-info/entry_points.txt
anton_testing_deleteme_123-3.0.0a1.dist-info/top_level.txt
anton_testing_deleteme_123-3.0.0a1.dist-info/RECORD
