Metadata-Version: 2.4
Name: anton-testing-deleteme-123
Version: 3.0.0a1
Summary: Python client for Sentry (https://sentry.io)
Home-page: https://github.com/getsentry/sentry-python
Author: Sentry Team and Contributors
Author-email: hello@sentry.io
License: MIT
Project-URL: Documentation, https://docs.sentry.io/platforms/python/
Project-URL: Changelog, https://github.com/getsentry/sentry-python/blob/master/CHANGELOG.md
Classifier: Development Status :: 5 - Production/Stable
Classifier: Environment :: Web Environment
Classifier: Intended Audience :: Developers
Classifier: License :: OSI Approved :: BSD License
Classifier: Operating System :: OS Independent
Classifier: Programming Language :: Python
Classifier: Programming Language :: Python :: 3
Classifier: Programming Language :: Python :: 3.7
Classifier: Programming Language :: Python :: 3.8
Classifier: Programming Language :: Python :: 3.9
Classifier: Programming Language :: Python :: 3.10
Classifier: Programming Language :: Python :: 3.11
Classifier: Programming Language :: Python :: 3.12
Classifier: Programming Language :: Python :: 3.13
Classifier: Topic :: Software Development :: Libraries :: Python Modules
Requires-Python: >=3.7
License-File: LICENSE
Requires-Dist: urllib3>=1.26.11
Requires-Dist: certifi
Requires-Dist: opentelemetry-sdk>=1.4.0
Provides-Extra: aiohttp
Requires-Dist: aiohttp>=3.5; extra == "aiohttp"
Provides-Extra: anthropic
Requires-Dist: anthropic>=0.16; extra == "anthropic"
Provides-Extra: arq
Requires-Dist: arq>=0.23; extra == "arq"
Provides-Extra: asyncpg
Requires-Dist: asyncpg>=0.23; extra == "asyncpg"
Provides-Extra: beam
Requires-Dist: apache-beam>=2.12; extra == "beam"
Provides-Extra: bottle
Requires-Dist: bottle>=0.12.13; extra == "bottle"
Provides-Extra: celery
Requires-Dist: celery>=3; extra == "celery"
Provides-Extra: celery-redbeat
Requires-Dist: celery-redbeat>=2; extra == "celery-redbeat"
Provides-Extra: chalice
Requires-Dist: chalice>=1.16.0; extra == "chalice"
Provides-Extra: clickhouse-driver
Requires-Dist: clickhouse-driver>=0.2.0; extra == "clickhouse-driver"
Provides-Extra: django
Requires-Dist: django>=1.8; extra == "django"
Provides-Extra: falcon
Requires-Dist: falcon>=1.4; extra == "falcon"
Provides-Extra: fastapi
Requires-Dist: fastapi>=0.79.0; extra == "fastapi"
Provides-Extra: flask
Requires-Dist: flask>=0.11; extra == "flask"
Requires-Dist: blinker>=1.1; extra == "flask"
Requires-Dist: markupsafe; extra == "flask"
Provides-Extra: grpcio
Requires-Dist: grpcio>=1.21.1; extra == "grpcio"
Requires-Dist: protobuf>=3.8.0; extra == "grpcio"
Provides-Extra: http2
Requires-Dist: httpcore[http2]==1.*; extra == "http2"
Provides-Extra: httpx
Requires-Dist: httpx>=0.16.0; extra == "httpx"
Provides-Extra: huey
Requires-Dist: huey>=2; extra == "huey"
Provides-Extra: huggingface-hub
Requires-Dist: huggingface_hub>=0.22; extra == "huggingface-hub"
Provides-Extra: langchain
Requires-Dist: langchain>=0.0.210; extra == "langchain"
Provides-Extra: launchdarkly
Requires-Dist: launchdarkly-server-sdk>=9.8.0; extra == "launchdarkly"
Provides-Extra: litestar
Requires-Dist: litestar>=2.0.0; extra == "litestar"
Provides-Extra: loguru
Requires-Dist: loguru>=0.5; extra == "loguru"
Provides-Extra: openai
Requires-Dist: openai>=1.0.0; extra == "openai"
Requires-Dist: tiktoken>=0.3.0; extra == "openai"
Provides-Extra: openfeature
Requires-Dist: openfeature-sdk>=0.7.1; extra == "openfeature"
Provides-Extra: opentelemetry
Requires-Dist: opentelemetry-distro>=0.35b0; extra == "opentelemetry"
Provides-Extra: pure-eval
Requires-Dist: pure_eval; extra == "pure-eval"
Requires-Dist: executing; extra == "pure-eval"
Requires-Dist: asttokens; extra == "pure-eval"
Provides-Extra: pymongo
Requires-Dist: pymongo>=3.1; extra == "pymongo"
Provides-Extra: pyspark
Requires-Dist: pyspark>=2.4.4; extra == "pyspark"
Provides-Extra: quart
Requires-Dist: quart>=0.16.1; extra == "quart"
Requires-Dist: blinker>=1.1; extra == "quart"
Provides-Extra: rq
Requires-Dist: rq>=0.6; extra == "rq"
Provides-Extra: sanic
Requires-Dist: sanic>=0.8; extra == "sanic"
Provides-Extra: sqlalchemy
Requires-Dist: sqlalchemy>=1.2; extra == "sqlalchemy"
Provides-Extra: starlette
Requires-Dist: starlette>=0.19.1; extra == "starlette"
Provides-Extra: starlite
Requires-Dist: starlite>=1.48; extra == "starlite"
Provides-Extra: statsig
Requires-Dist: statsig>=0.55.3; extra == "statsig"
Provides-Extra: tornado
Requires-Dist: tornado>=6; extra == "tornado"
Provides-Extra: unleash
Requires-Dist: UnleashClient>=6.0.1; extra == "unleash"
Dynamic: author
Dynamic: author-email
Dynamic: classifier
Dynamic: description
Dynamic: description-content-type
Dynamic: home-page
Dynamic: license
Dynamic: license-file
Dynamic: project-url
Dynamic: provides-extra
Dynamic: requires-dist
Dynamic: requires-python
Dynamic: summary
